pyttsx3/__init__.py
pyttsx3/driver.py
pyttsx3/engine.py
pyttsx3/six.py
pyttsx3/voice.py
pyttsx3/drivers/__init__.py
pyttsx3/drivers/_espeak.py
pyttsx3/drivers/dummy.py
pyttsx3/drivers/espeak.py
pyttsx3/drivers/nsss.py
pyttsx3/drivers/sapi5.py
pyttsx3-2.98.dist-info/LICENSE
pyttsx3-2.98.dist-info/METADATA
pyttsx3-2.98.dist-info/WHEEL
pyttsx3-2.98.dist-info/top_level.txt
pyttsx3-2.98.dist-info/RECORD
